{
  "fsize": 65536,
  "data": [
    {
      "name": "grass",
      "position": [
        -2.048139190673828,
        -38.959442138671875,
        -0.9999996185302734
      ],
      "shortparams": [
        0,
        0,
        0,
        0
      ],
      "intparams": [
        0,
        22,
        0,
        0,
        0
      ],
      "floatparams": [
        0.0,
        0.0,
        0.0,
        0.0,
        0.0
      ]
    },
    {
      "name": "grass",
      "position": [
        27.284396362304687,
        -38.967794799804686,
        -0.9999996185302734
      ],
      "shortparams": [
        0,
        0,
        0,
        0
      ],
      "intparams": [
        0,
        22,
        0,
        0,
        0
      ],
      "floatparams": [
        0.0,
        0.0,
        0.0,
        0.0,
        0.0
      ]
    },
    {
      "name": "grass",
      "position": [
        -19.246612548828125,
        164.4882568359375,
        -10.5800048828125
      ],
      "shortparams": [
        0,
        0,
        0,
        6656
      ],
      "intparams": [
        0,
        28,
        0,
        0,
        0
      ],
      "floatparams": [
        1.3000000715255737,
        0.0,
        0.0,
        0.0,
        0.0
      ]
    },
    {
      "name": "grass",
      "position": [
        48.20877380371094,
        17.43719482421875,
        -16.389999389648438
      ],
      "shortparams": [
        0,
        0,
        0,
        16384
      ],
      "intparams": [
        0,
        28,
        0,
        0,
        0
      ],
      "floatparams": [
        2.0,
        0.0,
        0.0,
        0.0,
        0.0
      ]
    },
    {
      "name": "unk263",
      "position": [
        264.5835693359375,
        -49.63211669921875,
        -8.253079223632813
      ],
      "shortparams": [
        0,
        0,
        0,
        0
      ],
      "intparams": [
        0,
        20,
        21,
        0,
        0
      ],
      "floatparams": [
        0.0,
        0.0,
        0.0,
        0.0,
        0.0
      ]
    },
    {
      "name": "unk262",
      "position": [
        232.1265380859375,
        -70.35231323242188,
        -15.013092041015625
      ],
      "shortparams": [
        0,
        0,
        0,
        0
      ],
      "intparams": [
        0,
        2,
        0,
        0,
        0
      ],
      "floatparams": [
        0.0,
        0.0,
        0.0,
        0.0,
        0.0
      ]
    },
    {
      "name": "unk262",
      "position": [
        205.48037109375,
        -70.83192138671875,
        -15.013092041015625
      ],
      "shortparams": [
        0,
        0,
        0,
        0
      ],
      "intparams": [
        0,
        1,
        0,
        0,
        0
      ],
      "floatparams": [
        0.0,
        0.0,
        0.0,
        0.0,
        0.0
      ]
    },
    {
      "name": "unk262",
      "position": [
        239.22177734375,
        -14.876077270507812,
        -15.013092041015625
      ],
      "shortparams": [
        0,
        0,
        0,
        -32000
      ],
      "intparams": [
        0,
        3,
        0,
        0,
        0
      ],
      "floatparams": [
        0.0,
        0.0,
        0.0,
        0.0,
        0.0
      ]
    },
    {
      "name": "unk262",
      "position": [
        204.8701171875,
        -13.607612609863281,
        -15.013092041015625
      ],
      "shortparams": [
        0,
        0,
        0,
        -32512
      ],
      "intparams": [
        0,
        4,
        0,
        0,
        0
      ],
      "floatparams": [
        0.0,
        0.0,
        0.0,
        0.0,
        0.0
      ]
    },
    {
      "name": "grass",
      "position": [
        300.857080078125,
        -54.34261474609375,
        -2.0
      ],
      "shortparams": [
        0,
        0,
        0,
        20480
      ],
      "intparams": [
        0,
        10,
        0,
        0,
        0
      ],
      "floatparams": [
        0.0,
        0.0,
        0.0,
        0.0,
        0.0
      ]
    },
    {
      "name": "grass",
      "position": [
        -35.707635498046876,
        170.64625244140626,
        -20.0
      ],
      "shortparams": [
        0,
        0,
        -1,
        -12544
      ],
      "intparams": [
        0,
        14,
        0,
        0,
        0
      ],
      "floatparams": [
        0.0,
        0.0,
        0.0,
        0.0,
        0.0
      ]
    },
    {
      "name": "grass",
      "position": [
        -52.70894775390625,
        20.925804138183594,
        -16.0
      ],
      "shortparams": [
        0,
        0,
        0,
        1024
      ],
      "intparams": [
        0,
        14,
        0,
        0,
        0
      ],
      "floatparams": [
        0.0,
        0.0,
        0.0,
        0.0,
        0.0
      ]
    },
    {
      "name": "grass",
      "position": [
        -48.620843505859376,
        20.745022583007813,
        -16.0
      ],
      "shortparams": [
        0,
        0,
        0,
        1024
      ],
      "intparams": [
        0,
        14,
        0,
        0,
        0
      ],
      "floatparams": [
        0.0,
        0.0,
        0.0,
        0.0,
        0.0
      ]
    },
    {
      "name": "grass",
      "position": [
        -38.954525756835935,
        20.517193603515626,
        -16.0
      ],
      "shortparams": [
        0,
        0,
        0,
        1024
      ],
      "intparams": [
        0,
        14,
        0,
        0,
        0
      ],
      "floatparams": [
        0.0,
        0.0,
        0.0,
        0.0,
        0.0
      ]
    },
    {
      "name": "grass",
      "position": [
        -43.44109191894531,
        20.731399536132812,
        -16.0
      ],
      "shortparams": [
        0,
        0,
        0,
        1024
      ],
      "intparams": [
        0,
        14,
        0,
        0,
        0
      ],
      "floatparams": [
        0.0,
        0.0,
        0.0,
        0.0,
        0.0
      ]
    },
    {
      "name": "grass",
      "position": [
        -94.13795166015625,
        -159.1175048828125,
        -12.0
      ],
      "shortparams": [
        0,
        0,
        0,
        25856
      ],
      "intparams": [
        0,
        1,
        0,
        0,
        0
      ],
      "floatparams": [
        0.0,
        0.0,
        0.0,
        0.0,
        0.0
      ]
    },
    {
      "name": "grass",
      "position": [
        -91.16080932617187,
        -159.10548095703126,
        -12.0
      ],
      "shortparams": [
        0,
        0,
        0,
        -28672
      ],
      "intparams": [
        0,
        1,
        0,
        0,
        0
      ],
      "floatparams": [
        0.0,
        0.0,
        0.0,
        0.0,
        0.0
      ]
    },
    {
      "name": "grass",
      "position": [
        -92.0473388671875,
        -161.00404052734376,
        -12.0
      ],
      "shortparams": [
        0,
        0,
        0,
        12288
      ],
      "intparams": [
        0,
        1,
        0,
        0,
        0
      ],
      "floatparams": [
        0.0,
        0.0,
        0.0,
        0.0,
        0.0
      ]
    },
    {
      "name": "grass",
      "position": [
        -34.200704956054686,
        174.424072265625,
        -20.0
      ],
      "shortparams": [
        0,
        0,
        -1,
        19200
      ],
      "intparams": [
        0,
        14,
        0,
        0,
        0
      ],
      "floatparams": [
        0.0,
        0.0,
        0.0,
        0.0,
        0.0
      ]
    },
    {
      "name": "grass",
      "position": [
        105.3820068359375,
        110.19100341796874,
        -1.0
      ],
      "shortparams": [
        0,
        0,
        0,
        0
      ],
      "intparams": [
        0,
        35,
        0,
        0,
        0
      ],
      "floatparams": [
        0.0,
        0.0,
        0.0,
        0.0,
        0.0
      ]
    },
    {
      "name": "grass",
      "position": [
        47.07743835449219,
        -4.842339324951172,
        -30.0
      ],
      "shortparams": [
        0,
        0,
        0,
        0
      ],
      "intparams": [
        0,
        36,
        0,
        0,
        0
      ],
      "floatparams": [
        0.0,
        0.0,
        0.0,
        0.0,
        0.0
      ]
    },
    {
      "name": "unk264",
      "position": [
        -75.81030883789063,
        -128.669580078125,
        -2.4730525970458985
      ],
      "shortparams": [
        0,
        0,
        -1,
        -12288
      ],
      "intparams": [
        0,
        1,
        0,
        0,
        0
      ],
      "floatparams": [
        0.0,
        0.0,
        0.0,
        0.0,
        0.0
      ]
    },
    {
      "name": "unk265",
      "position": [
        47.38199157714844,
        -5.128118515014648,
        -39.46000671386719
      ],
      "shortparams": [
        0,
        0,
        0,
        0
      ],
      "intparams": [
        0,
        5,
        1,
        90,
        800
      ],
      "floatparams": [
        0.4000000059604645,
        0.8000000715255737,
        -0.14999999105930328,
        -0.050000011920928955,
        0.0
      ]
    },
    {
      "name": "gate",
      "position": [
        57.37266845703125,
        73.57936401367188,
        -20.0
      ],
      "shortparams": [
        0,
        0,
        0,
        0
      ],
      "intparams": [
        0,
        0,
        0,
        0,
        3
      ],
      "floatparams": [
        0.0,
        0.0,
        0.0,
        0.0,
        0.0
      ]
    },
    {
      "name": "unk265",
      "position": [
        -33.88685913085938,
        169.07874755859376,
        -29.68001708984375
      ],
      "shortparams": [
        0,
        0,
        0,
        0
      ],
      "intparams": [
        0,
        5,
        1,
        40,
        180
      ],
      "floatparams": [
        -0.10000000149011612,
        0.10000001639127731,
        -0.14999999105930328,
        -0.050000011920928955,
        0.0
      ]
    },
    {
      "name": "gate",
      "position": [
        -150.77547607421874,
        -188.5326171875,
        -17.0
      ],
      "shortparams": [
        0,
        0,
        -1,
        -19456
      ],
      "intparams": [
        0,
        1,
        0,
        0,
        4
      ],
      "floatparams": [
        0.0,
        0.0,
        0.0,
        0.0,
        0.0
      ]
    },
    {
      "name": "unk29",
      "position": [
        56.07698974609375,
        61.87998046875,
        -19.999736022949218
      ],
      "shortparams": [
        0,
        0,
        0,
        -4096
      ],
      "intparams": [
        0,
        900,
        80,
        0,
        0
      ],
      "floatparams": [
        0.0,
        60.0,
        -60.0,
        60.0,
        0.0
      ]
    },
    {
      "name": "fruit",
      "position": [
        -46.260565185546874,
        1.7690254211425782,
        -16.0
      ],
      "shortparams": [
        0,
        0,
        0,
        0
      ],
      "intparams": [
        0,
        1,
        0,
        1,
        0
      ],
      "floatparams": [
        0.0,
        0.0,
        0.0,
        0.0,
        0.0
      ]
    },
    {
      "name": "unk15",
      "position": [
        108.4916259765625,
        -49.25386352539063,
        -5.0
      ],
      "shortparams": [
        0,
        0,
        -1,
        -16384
      ],
      "intparams": [
        0,
        10,
        0,
        0,
        0
      ],
      "floatparams": [
        90.0,
        0.0,
        0.0,
        0.0,
        0.0
      ]
    },
    {
      "name": "grass",
      "position": [
        53.582086181640626,
        -4.101035690307617,
        -30.0
      ],
      "shortparams": [
        0,
        0,
        -1,
        -2560
      ],
      "intparams": [
        0,
        16,
        0,
        0,
        0
      ],
      "floatparams": [
        0.0,
        0.0,
        0.0,
        0.0,
        0.0
      ]
    },
    {
      "name": "grass",
      "position": [
        49.542257690429686,
        -4.8188331604003904,
        -30.0
      ],
      "shortparams": [
        0,
        0,
        -1,
        -2560
      ],
      "intparams": [
        0,
        16,
        0,
        0,
        0
      ],
      "floatparams": [
        0.0,
        0.0,
        0.0,
        0.0,
        0.0
      ]
    },
    {
      "name": "unk257",
      "position": [
        100.34594116210937,
        8.948300170898438,
        -18.193087768554687
      ],
      "shortparams": [
        0,
        0,
        -1,
        -2816
      ],
      "intparams": [
        0,
        300,
        1000,
        0,
        0
      ],
      "floatparams": [
        0.0,
        0.0,
        0.0,
        0.0,
        0.0
      ]
    },
    {
      "name": "unk257",
      "position": [
        95.80524291992188,
        24.190940856933594,
        -18.193087768554687
      ],
      "shortparams": [
        0,
        0,
        -1,
        -3072
      ],
      "intparams": [
        0,
        300,
        800,
        0,
        0
      ],
      "floatparams": [
        0.0,
        0.0,
        0.0,
        0.0,
        0.0
      ]
    },
    {
      "name": "firepillar",
      "position": [
        84.16033935546875,
        65.24889526367187,
        -7.0
      ],
      "shortparams": [
        0,
        0,
        0,
        0
      ],
      "intparams": [
        0,
        0,
        -2,
        0,
        0
      ],
      "floatparams": [
        0.0,
        0.0,
        0.0,
        0.0,
        0.0
      ]
    },
    {
      "name": "firepillar",
      "position": [
        86.37136840820312,
        65.98295288085937,
        -7.0
      ],
      "shortparams": [
        0,
        0,
        0,
        0
      ],
      "intparams": [
        0,
        0,
        -2,
        0,
        0
      ],
      "floatparams": [
        0.0,
        0.0,
        0.0,
        0.0,
        0.0
      ]
    },
    {
      "name": "firepillar",
      "position": [
        88.544775390625,
        66.68767700195312,
        -7.0
      ],
      "shortparams": [
        0,
        0,
        0,
        0
      ],
      "intparams": [
        0,
        0,
        -2,
        0,
        0
      ],
      "floatparams": [
        0.0,
        0.0,
        0.0,
        0.0,
        0.0
      ]
    },
    {
      "name": "checkpoint",
      "position": [
        103.43291015625,
        -48.74991149902344,
        -5.0
      ],
      "shortparams": [
        0,
        0,
        0,
        0
      ],
      "intparams": [
        0,
        10,
        0,
        0,
        0
      ],
      "floatparams": [
        90.0,
        0.0,
        0.0,
        0.0,
        0.0
      ]
    },
    {
      "name": "hoop",
      "position": [
        105.333642578125,
        -25.649996948242187,
        -9.37607650756836
      ],
      "shortparams": [
        0,
        0,
        -1,
        -31488
      ],
      "intparams": [
        0,
        3,
        100,
        0,
        0
      ],
      "floatparams": [
        2.0,
        0.0,
        100.0,
        0.0,
        0.0
      ]
    },
    {
      "name": "hoop",
      "position": [
        92.95607299804688,
        -47.08586120605469,
        -6.446076965332031
      ],
      "shortparams": [
        -1,
        -1280,
        -1,
        -17152
      ],
      "intparams": [
        0,
        3,
        100,
        0,
        0
      ],
      "floatparams": [
        2.0,
        0.0,
        100.0,
        0.0,
        0.0
      ]
    },
    {
      "name": "gate",
      "position": [
        71.39490966796875,
        -48.6790771484375,
        -5.0
      ],
      "shortparams": [
        0,
        0,
        -1,
        -14848
      ],
      "intparams": [
        0,
        0,
        0,
        0,
        1
      ],
      "floatparams": [
        0.0,
        0.0,
        0.0,
        0.0,
        0.0
      ]
    },
    {
      "name": "hoop",
      "position": [
        -24.527407836914062,
        -82.0034423828125,
        -24.411915588378907
      ],
      "shortparams": [
        0,
        0,
        0,
        0
      ],
      "intparams": [
        0,
        2,
        300,
        0,
        0
      ],
      "floatparams": [
        0.0,
        0.0,
        0.0,
        0.0,
        0.0
      ]
    },
    {
      "name": "hoop",
      "position": [
        -21.579383850097656,
        -5.726193618774414,
        -8.121905517578124
      ],
      "shortparams": [
        0,
        0,
        0,
        0
      ],
      "intparams": [
        0,
        2,
        140,
        0,
        0
      ],
      "floatparams": [
        0.0,
        0.0,
        0.0,
        0.0,
        0.0
      ]
    },
    {
      "name": "hoop",
      "position": [
        -10.775962829589844,
        -71.641259765625,
        -22.401910400390626
      ],
      "shortparams": [
        0,
        0,
        -1,
        -26880
      ],
      "intparams": [
        0,
        3,
        100,
        0,
        0
      ],
      "floatparams": [
        2.0,
        0.0,
        50.0,
        0.0,
        0.0
      ]
    },
    {
      "name": "grass",
      "position": [
        -36.47108459472656,
        18.89928436279297,
        -16.0
      ],
      "shortparams": [
        0,
        0,
        0,
        -31744
      ],
      "intparams": [
        0,
        3,
        1,
        0,
        0
      ],
      "floatparams": [
        0.0,
        0.0,
        0.0,
        0.0,
        0.0
      ]
    },
    {
      "name": "hoop",
      "position": [
        112.377392578125,
        79.07918090820313,
        -13.083079528808593
      ],
      "shortparams": [
        0,
        0,
        0,
        -24832
      ],
      "intparams": [
        0,
        3,
        300,
        0,
        0
      ],
      "floatparams": [
        3.0,
        0.0,
        100.0,
        0.0,
        0.0
      ]
    },
    {
      "name": "hoop",
      "position": [
        109.36734619140626,
        94.9609130859375,
        -13.083079528808593
      ],
      "shortparams": [
        0,
        0,
        0,
        30720
      ],
      "intparams": [
        0,
        3,
        200,
        0,
        0
      ],
      "floatparams": [
        3.0,
        0.0,
        100.0,
        0.0,
        0.0
      ]
    },
    {
      "name": "hoop",
      "position": [
        99.76963500976562,
        107.714453125,
        -13.083079528808593
      ],
      "shortparams": [
        0,
        0,
        0,
        26624
      ],
      "intparams": [
        0,
        3,
        200,
        0,
        0
      ],
      "floatparams": [
        3.0,
        0.0,
        100.0,
        0.0,
        0.0
      ]
    },
    {
      "name": "hoop",
      "position": [
        101.08753051757813,
        67.64368896484375,
        -13.083079528808593
      ],
      "shortparams": [
        0,
        0,
        0,
        -20736
      ],
      "intparams": [
        0,
        3,
        100,
        0,
        0
      ],
      "floatparams": [
        3.0,
        0.0,
        60.0,
        0.0,
        0.0
      ]
    },
    {
      "name": "hoop",
      "position": [
        13.984185791015625,
        9.818873596191406,
        -24.6150634765625
      ],
      "shortparams": [
        0,
        0,
        0,
        12288
      ],
      "intparams": [
        0,
        0,
        200,
        0,
        0
      ],
      "floatparams": [
        0.0,
        0.0,
        0.0,
        0.0,
        0.0
      ]
    },
    {
      "name": "grass",
      "position": [
        44.30179138183594,
        -5.2991081237792965,
        -5.0
      ],
      "shortparams": [
        0,
        0,
        0,
        6144
      ],
      "intparams": [
        0,
        3,
        1,
        0,
        0
      ],
      "floatparams": [
        0.0,
        0.0,
        0.0,
        0.0,
        0.0
      ]
    },
    {
      "name": "grass",
      "position": [
        84.3669189453125,
        136.72772216796875,
        -6.0
      ],
      "shortparams": [
        0,
        0,
        0,
        22784
      ],
      "intparams": [
        0,
        1,
        1,
        0,
        0
      ],
      "floatparams": [
        0.0,
        0.0,
        0.0,
        0.0,
        0.0
      ]
    },
    {
      "name": "grass",
      "position": [
        78.74047241210937,
        137.552685546875,
        -6.0
      ],
      "shortparams": [
        0,
        0,
        0,
        22784
      ],
      "intparams": [
        0,
        1,
        1,
        0,
        0
      ],
      "floatparams": [
        0.0,
        0.0,
        0.0,
        0.0,
        0.0
      ]
    },
    {
      "name": "grass",
      "position": [
        81.2322998046875,
        141.55262451171876,
        -6.0
      ],
      "shortparams": [
        0,
        0,
        0,
        22784
      ],
      "intparams": [
        0,
        1,
        1,
        0,
        0
      ],
      "floatparams": [
        0.0,
        0.0,
        0.0,
        0.0,
        0.0
      ]
    },
    {
      "name": "eggbounceswitch",
      "position": [
        57.04502563476562,
        81.79462890625,
        -20.0
      ],
      "shortparams": [
        0,
        0,
        0,
        0
      ],
      "intparams": [
        0,
        1,
        0,
        0,
        3
      ],
      "floatparams": [
        0.0,
        0.0,
        0.0,
        0.0,
        0.0
      ]
    },
    {
      "name": "unk18",
      "position": [
        93.81528930664062,
        108.5198974609375,
        -11.0
      ],
      "shortparams": [
        0,
        0,
        0,
        0
      ],
      "intparams": [
        0,
        3,
        0,
        5,
        1
      ],
      "floatparams": [
        0.0,
        0.0,
        0.0,
        0.0,
        0.0
      ]
    },
    {
      "name": "egg",
      "position": [
        23.451199340820313,
        86.52288208007812,
        -10.0
      ],
      "shortparams": [
        0,
        0,
        0,
        0
      ],
      "intparams": [
        0,
        0,
        0,
        0,
        0
      ],
      "floatparams": [
        0.0,
        0.0,
        0.0,
        0.0,
        0.0
      ]
    },
    {
      "name": "grass",
      "position": [
        23.451199340820313,
        86.52288208007812,
        -10.0
      ],
      "shortparams": [
        0,
        0,
        0,
        0
      ],
      "intparams": [
        0,
        0,
        1,
        0,
        0
      ],
      "floatparams": [
        0.0,
        0.0,
        0.0,
        0.0,
        0.0
      ]
    },
    {
      "name": "hoop",
      "position": [
        89.84246215820312,
        126.49683837890625,
        -9.073084259033203
      ],
      "shortparams": [
        0,
        0,
        0,
        0
      ],
      "intparams": [
        0,
        2,
        200,
        0,
        0
      ],
      "floatparams": [
        0.0,
        0.0,
        0.0,
        0.0,
        0.0
      ]
    },
    {
      "name": "grass",
      "position": [
        49.279501342773436,
        135.4583251953125,
        -4.0
      ],
      "shortparams": [
        0,
        0,
        0,
        0
      ],
      "intparams": [
        0,
        0,
        1,
        0,
        0
      ],
      "floatparams": [
        0.0,
        0.0,
        0.0,
        0.0,
        0.0
      ]
    },
    {
      "name": "egg",
      "position": [
        49.2494140625,
        135.4892333984375,
        -4.0
      ],
      "shortparams": [
        0,
        0,
        0,
        0
      ],
      "intparams": [
        0,
        0,
        0,
        0,
        0
      ],
      "floatparams": [
        0.0,
        0.0,
        0.0,
        0.0,
        0.0
      ]
    },
    {
      "name": "grass",
      "position": [
        15.377693176269531,
        132.3132568359375,
        -4.0
      ],
      "shortparams": [
        0,
        0,
        0,
        25600
      ],
      "intparams": [
        0,
        3,
        1,
        0,
        0
      ],
      "floatparams": [
        0.0,
        0.0,
        0.0,
        0.0,
        0.0
      ]
    },
    {
      "name": "grass",
      "position": [
        86.70166625976563,
        46.510137939453124,
        -7.0
      ],
      "shortparams": [
        0,
        0,
        0,
        0
      ],
      "intparams": [
        0,
        0,
        1,
        0,
        0
      ],
      "floatparams": [
        0.0,
        0.0,
        0.0,
        0.0,
        0.0
      ]
    },
    {
      "name": "firepillar",
      "position": [
        82.13193969726562,
        64.59495849609375,
        -7.0
      ],
      "shortparams": [
        0,
        0,
        0,
        0
      ],
      "intparams": [
        0,
        0,
        -2,
        0,
        0
      ],
      "floatparams": [
        0.0,
        0.0,
        0.0,
        0.0,
        0.0
      ]
    },
    {
      "name": "firepillar",
      "position": [
        89.21451416015626,
        38.92495422363281,
        -7.0
      ],
      "shortparams": [
        0,
        0,
        0,
        0
      ],
      "intparams": [
        0,
        0,
        0,
        0,
        0
      ],
      "floatparams": [
        0.0,
        0.0,
        0.0,
        0.0,
        0.0
      ]
    },
    {
      "name": "firepillar",
      "position": [
        91.27305297851562,
        39.50076904296875,
        -7.0
      ],
      "shortparams": [
        0,
        0,
        0,
        0
      ],
      "intparams": [
        0,
        0,
        0,
        0,
        0
      ],
      "floatparams": [
        0.0,
        0.0,
        0.0,
        0.0,
        0.0
      ]
    },
    {
      "name": "firepillar",
      "position": [
        93.4146240234375,
        40.11275024414063,
        -7.0
      ],
      "shortparams": [
        0,
        0,
        0,
        0
      ],
      "intparams": [
        0,
        0,
        0,
        0,
        0
      ],
      "floatparams": [
        0.0,
        0.0,
        0.0,
        0.0,
        0.0
      ]
    },
    {
      "name": "firepillar",
      "position": [
        95.51444091796876,
        40.87974243164062,
        -7.0
      ],
      "shortparams": [
        0,
        0,
        0,
        0
      ],
      "intparams": [
        0,
        0,
        0,
        0,
        0
      ],
      "floatparams": [
        0.0,
        0.0,
        0.0,
        0.0,
        0.0
      ]
    },
    {
      "name": "eggbounceswitch",
      "position": [
        98.30269165039063,
        -46.638327026367186,
        -5.0
      ],
      "shortparams": [
        0,
        0,
        0,
        0
      ],
      "intparams": [
        0,
        0,
        0,
        0,
        1
      ],
      "floatparams": [
        0.0,
        0.0,
        0.0,
        0.0,
        0.0
      ]
    },
    {
      "name": "grass",
      "position": [
        18.789518737792967,
        -3.325613021850586,
        -5.0
      ],
      "shortparams": [
        0,
        0,
        -1,
        -17408
      ],
      "intparams": [
        0,
        1,
        1,
        0,
        0
      ],
      "floatparams": [
        0.0,
        0.0,
        0.0,
        0.0,
        0.0
      ]
    },
    {
      "name": "grass",
      "position": [
        19.458961486816406,
        -8.570772552490235,
        -5.0
      ],
      "shortparams": [
        0,
        0,
        -1,
        -17408
      ],
      "intparams": [
        0,
        1,
        1,
        0,
        0
      ],
      "floatparams": [
        0.0,
        0.0,
        0.0,
        0.0,
        0.0
      ]
    },
    {
      "name": "grass",
      "position": [
        14.107264709472656,
        -6.424549102783203,
        -5.0
      ],
      "shortparams": [
        0,
        0,
        -1,
        -17408
      ],
      "intparams": [
        0,
        1,
        1,
        0,
        0
      ],
      "floatparams": [
        0.0,
        0.0,
        0.0,
        0.0,
        0.0
      ]
    },
    {
      "name": "hoop",
      "position": [
        -9.342339324951173,
        -69.67601318359375,
        -7.651892852783203
      ],
      "shortparams": [
        0,
        0,
        0,
        0
      ],
      "intparams": [
        0,
        2,
        300,
        0,
        0
      ],
      "floatparams": [
        0.0,
        0.0,
        0.0,
        0.0,
        0.0
      ]
    },
    {
      "name": "grass",
      "position": [
        57.9048095703125,
        -3.2763999938964843,
        -30.0
      ],
      "shortparams": [
        0,
        0,
        -1,
        -2560
      ],
      "intparams": [
        0,
        16,
        0,
        0,
        0
      ],
      "floatparams": [
        0.0,
        0.0,
        0.0,
        0.0,
        0.0
      ]
    },
    {
      "name": "grass",
      "position": [
        55.19261474609375,
        17.199919128417967,
        -30.0
      ],
      "shortparams": [
        0,
        0,
        -1,
        -512
      ],
      "intparams": [
        0,
        1,
        1,
        0,
        0
      ],
      "floatparams": [
        0.0,
        0.0,
        0.0,
        0.0,
        0.0
      ]
    },
    {
      "name": "egg",
      "position": [
        86.655322265625,
        46.41616516113281,
        -7.0
      ],
      "shortparams": [
        0,
        0,
        0,
        0
      ],
      "intparams": [
        0,
        0,
        0,
        0,
        0
      ],
      "floatparams": [
        0.0,
        0.0,
        0.0,
        0.0,
        0.0
      ]
    },
    {
      "name": "unk40",
      "position": [
        -26.253131103515624,
        170.5968994140625,
        -20.0
      ],
      "shortparams": [
        0,
        0,
        -1,
        -28672
      ],
      "intparams": [
        0,
        1,
        1,
        0,
        0
      ],
      "floatparams": [
        0.0,
        0.0,
        0.0,
        0.0,
        3.1591410678348977e-38
      ]
    },
    {
      "name": "unk39",
      "position": [
        -24.80086669921875,
        169.62794189453126,
        -20.0
      ],
      "shortparams": [
        0,
        0,
        0,
        0
      ],
      "intparams": [
        0,
        5,
        256,
        0,
        0
      ],
      "floatparams": [
        0.0,
        0.0,
        0.0,
        0.0,
        0.0
      ]
    },
    {
      "name": "hoop",
      "position": [
        26.082424926757813,
        4.333881759643555,
        -27.545065307617186
      ],
      "shortparams": [
        0,
        0,
        0,
        0
      ],
      "intparams": [
        0,
        0,
        200,
        0,
        0
      ],
      "floatparams": [
        0.0,
        0.0,
        0.0,
        0.0,
        0.0
      ]
    },
    {
      "name": "hoop",
      "position": [
        5.285955810546875,
        107.46171875,
        -10.715058898925781
      ],
      "shortparams": [
        0,
        0,
        -1,
        -12288
      ],
      "intparams": [
        0,
        0,
        200,
        0,
        0
      ],
      "floatparams": [
        0.0,
        0.0,
        0.0,
        0.0,
        0.0
      ]
    },
    {
      "name": "hoop",
      "position": [
        -4.070172500610352,
        118.78363037109375,
        -13.145059204101562
      ],
      "shortparams": [
        0,
        0,
        -1,
        -17408
      ],
      "intparams": [
        0,
        0,
        200,
        0,
        0
      ],
      "floatparams": [
        0.0,
        0.0,
        0.0,
        0.0,
        0.0
      ]
    },
    {
      "name": "hoop",
      "position": [
        -9.8417724609375,
        106.62376708984375,
        -13.145059204101562
      ],
      "shortparams": [
        0,
        0,
        -1,
        -6656
      ],
      "intparams": [
        0,
        0,
        200,
        0,
        0
      ],
      "floatparams": [
        0.0,
        0.0,
        0.0,
        0.0,
        0.0
      ]
    },
    {
      "name": "hoop",
      "position": [
        -31.31727294921875,
        125.0998046875,
        -18.135057067871095
      ],
      "shortparams": [
        0,
        0,
        -1,
        -12032
      ],
      "intparams": [
        0,
        0,
        200,
        0,
        0
      ],
      "floatparams": [
        0.0,
        0.0,
        0.0,
        0.0,
        0.0
      ]
    },
    {
      "name": "hoop",
      "position": [
        53.63161010742188,
        11.687261962890625,
        -35.0
      ],
      "shortparams": [
        0,
        0,
        0,
        0
      ],
      "intparams": [
        0,
        2,
        200,
        0,
        0
      ],
      "floatparams": [
        50.0,
        200.0,
        0.0,
        0.0,
        0.0
      ]
    },
    {
      "name": "grass",
      "position": [
        61.159307861328124,
        151.66749267578126,
        -4.0
      ],
      "shortparams": [
        0,
        0,
        0,
        -31744
      ],
      "intparams": [
        0,
        3,
        1,
        0,
        0
      ],
      "floatparams": [
        0.0,
        0.0,
        0.0,
        0.0,
        0.0
      ]
    },
    {
      "name": "grass",
      "position": [
        15.683073425292969,
        116.339794921875,
        -10.0
      ],
      "shortparams": [
        0,
        0,
        0,
        -7168
      ],
      "intparams": [
        0,
        3,
        1,
        0,
        0
      ],
      "floatparams": [
        0.0,
        0.0,
        0.0,
        0.0,
        0.0
      ]
    },
    {
      "name": "hoop",
      "position": [
        53.44744873046875,
        12.074501037597656,
        -44.06997985839844
      ],
      "shortparams": [
        0,
        0,
        -1,
        -4096
      ],
      "intparams": [
        0,
        3,
        200,
        0,
        0
      ],
      "floatparams": [
        3.0,
        0.0,
        50.0,
        0.0,
        0.0
      ]
    },
    {
      "name": "hoop",
      "position": [
        50.027618408203125,
        19.264208984375,
        -44.06997985839844
      ],
      "shortparams": [
        0,
        0,
        -1,
        -4096
      ],
      "intparams": [
        0,
        3,
        200,
        0,
        0
      ],
      "floatparams": [
        3.0,
        0.0,
        50.0,
        0.0,
        0.0
      ]
    },
    {
      "name": "hoop",
      "position": [
        46.43456115722656,
        26.81800231933594,
        -44.06997985839844
      ],
      "shortparams": [
        0,
        0,
        -1,
        -4096
      ],
      "intparams": [
        0,
        3,
        200,
        0,
        0
      ],
      "floatparams": [
        3.0,
        0.0,
        50.0,
        0.0,
        0.0
      ]
    },
    {
      "name": "hoop",
      "position": [
        43.28959655761719,
        33.42972412109375,
        -44.06997985839844
      ],
      "shortparams": [
        0,
        4096,
        -1,
        -4096
      ],
      "intparams": [
        0,
        3,
        200,
        0,
        0
      ],
      "floatparams": [
        3.0,
        0.0,
        50.0,
        0.0,
        0.0
      ]
    },
    {
      "name": "hoop",
      "position": [
        40.51991577148438,
        40.221066284179685,
        -40.0099853515625
      ],
      "shortparams": [
        0,
        4096,
        -1,
        -4096
      ],
      "intparams": [
        0,
        3,
        200,
        0,
        0
      ],
      "floatparams": [
        3.0,
        0.0,
        50.0,
        0.0,
        0.0
      ]
    },
    {
      "name": "hoop",
      "position": [
        37.901022338867186,
        46.555389404296875,
        -36.009970092773436
      ],
      "shortparams": [
        0,
        4096,
        0,
        0
      ],
      "intparams": [
        0,
        3,
        200,
        0,
        0
      ],
      "floatparams": [
        3.0,
        0.0,
        50.0,
        0.0,
        0.0
      ]
    },
    {
      "name": "hoop",
      "position": [
        37.627252197265626,
        52.56517333984375,
        -32.329962158203124
      ],
      "shortparams": [
        0,
        4096,
        0,
        0
      ],
      "intparams": [
        0,
        3,
        200,
        0,
        0
      ],
      "floatparams": [
        3.0,
        0.0,
        50.0,
        0.0,
        0.0
      ]
    },
    {
      "name": "hoop",
      "position": [
        37.34706420898438,
        58.71559448242188,
        -27.509951782226562
      ],
      "shortparams": [
        0,
        1792,
        0,
        0
      ],
      "intparams": [
        0,
        3,
        200,
        0,
        0
      ],
      "floatparams": [
        3.0,
        0.0,
        50.0,
        0.0,
        0.0
      ]
    },
    {
      "name": "hoop",
      "position": [
        37.4309814453125,
        65.19822387695312,
        -25.719952392578126
      ],
      "shortparams": [
        -1,
        -1024,
        0,
        0
      ],
      "intparams": [
        0,
        3,
        200,
        0,
        0
      ],
      "floatparams": [
        3.0,
        0.0,
        50.0,
        0.0,
        0.0
      ]
    },
    {
      "name": "grass",
      "position": [
        -17.529568481445313,
        168.18497314453126,
        -20.0
      ],
      "shortparams": [
        0,
        0,
        -1,
        16384
      ],
      "intparams": [
        0,
        14,
        0,
        0,
        0
      ],
      "floatparams": [
        0.0,
        0.0,
        0.0,
        0.0,
        0.0
      ]
    },
    {
      "name": "grass",
      "position": [
        -17.515225219726563,
        172.4007080078125,
        -20.0
      ],
      "shortparams": [
        0,
        0,
        -1,
        16384
      ],
      "intparams": [
        0,
        14,
        0,
        0,
        0
      ],
      "floatparams": [
        0.0,
        0.0,
        0.0,
        0.0,
        0.0
      ]
    },
    {
      "name": "grass",
      "position": [
        -26.98487243652344,
        179.69720458984375,
        -20.0
      ],
      "shortparams": [
        0,
        0,
        -2,
        -2304
      ],
      "intparams": [
        0,
        14,
        0,
        0,
        0
      ],
      "floatparams": [
        0.0,
        0.0,
        0.0,
        0.0,
        0.0
      ]
    },
    {
      "name": "grass",
      "position": [
        -31.309149169921874,
        178.71488037109376,
        -20.0
      ],
      "shortparams": [
        0,
        0,
        -2,
        -2304
      ],
      "intparams": [
        0,
        14,
        0,
        0,
        0
      ],
      "floatparams": [
        0.0,
        0.0,
        0.0,
        0.0,
        0.0
      ]
    },
    {
      "name": "grass",
      "position": [
        -34.04914245605469,
        168.5626953125,
        -20.0
      ],
      "shortparams": [
        0,
        0,
        -1,
        -9984
      ],
      "intparams": [
        0,
        36,
        0,
        0,
        0
      ],
      "floatparams": [
        0.0,
        0.0,
        0.0,
        0.0,
        0.0
      ]
    },
    {
      "name": "emblem",
      "position": [
        -29.31451416015625,
        169.65126953125,
        -22.0
      ],
      "shortparams": [
        0,
        0,
        0,
        24576
      ],
      "intparams": [
        0,
        1,
        250,
        0,
        0
      ],
      "floatparams": [
        0.0,
        0.0,
        0.0,
        0.0,
        2.369355800876173e-38
      ]
    },
    {
      "name": "grass",
      "position": [
        -58.323211669921875,
        132.522900390625,
        -20.0
      ],
      "shortparams": [
        0,
        0,
        0,
        20480
      ],
      "intparams": [
        0,
        3,
        1,
        0,
        0
      ],
      "floatparams": [
        0.0,
        0.0,
        0.0,
        0.0,
        0.0
      ]
    },
    {
      "name": "chickcoin",
      "position": [
        78.93457641601563,
        137.4929931640625,
        -7.473094940185547
      ],
      "shortparams": [
        0,
        0,
        0,
        0
      ],
      "intparams": [
        0,
        55,
        0,
        0,
        0
      ],
      "floatparams": [
        0.0,
        0.0,
        0.0,
        0.0,
        0.0
      ]
    },
    {
      "name": "chickcoin",
      "position": [
        -42.41094970703125,
        -9.850040435791016,
        -25.643099975585937
      ],
      "shortparams": [
        0,
        0,
        0,
        0
      ],
      "intparams": [
        0,
        56,
        0,
        0,
        0
      ],
      "floatparams": [
        0.0,
        0.0,
        0.0,
        0.0,
        0.0
      ]
    },
    {
      "name": "chickcoin",
      "position": [
        18.0477783203125,
        4.525999069213867,
        -27.333099365234375
      ],
      "shortparams": [
        0,
        0,
        0,
        0
      ],
      "intparams": [
        0,
        57,
        0,
        0,
        0
      ],
      "floatparams": [
        0.0,
        0.0,
        0.0,
        0.0,
        0.0
      ]
    },
    {
      "name": "egg",
      "position": [
        105.3820068359375,
        110.19100341796874,
        -1.0
      ],
      "shortparams": [
        0,
        0,
        0,
        0
      ],
      "intparams": [
        0,
        49,
        0,
        0,
        0
      ],
      "floatparams": [
        0.0,
        0.0,
        0.0,
        0.0,
        0.0
      ]
    },
    {
      "name": "grass",
      "position": [
        49.90772705078125,
        -23.67041931152344,
        -30.0
      ],
      "shortparams": [
        0,
        0,
        0,
        0
      ],
      "intparams": [
        0,
        0,
        1,
        0,
        0
      ],
      "floatparams": [
        0.0,
        0.0,
        0.0,
        0.0,
        0.0
      ]
    },
    {
      "name": "egg",
      "position": [
        49.90772705078125,
        -23.67041931152344,
        -30.0
      ],
      "shortparams": [
        0,
        0,
        0,
        0
      ],
      "intparams": [
        0,
        23,
        0,
        0,
        0
      ],
      "floatparams": [
        0.0,
        0.0,
        0.0,
        0.0,
        0.0
      ]
    },
    {
      "name": "hoop",
      "position": [
        -20.481875610351562,
        115.86302490234375,
        -16.03505096435547
      ],
      "shortparams": [
        0,
        0,
        -1,
        -1792
      ],
      "intparams": [
        0,
        0,
        200,
        0,
        0
      ],
      "floatparams": [
        0.0,
        0.0,
        0.0,
        0.0,
        0.0
      ]
    },
    {
      "name": "chickcoin",
      "position": [
        -6.242787551879883,
        112.270849609375,
        -13.57308349609375
      ],
      "shortparams": [
        0,
        0,
        0,
        0
      ],
      "intparams": [
        0,
        59,
        0,
        0,
        0
      ],
      "floatparams": [
        0.0,
        0.0,
        0.0,
        0.0,
        0.0
      ]
    },
    {
      "name": "grass",
      "position": [
        51.55611572265625,
        17.007099914550782,
        -30.0
      ],
      "shortparams": [
        0,
        0,
        -1,
        -512
      ],
      "intparams": [
        0,
        1,
        1,
        0,
        0
      ],
      "floatparams": [
        0.0,
        0.0,
        0.0,
        0.0,
        0.0
      ]
    },
    {
      "name": "grass",
      "position": [
        59.6145263671875,
        7.215827941894531,
        -29.890008544921876
      ],
      "shortparams": [
        0,
        0,
        1,
        15104
      ],
      "intparams": [
        0,
        3,
        1,
        0,
        0
      ],
      "floatparams": [
        0.0,
        0.0,
        0.0,
        0.0,
        0.0
      ]
    },
    {
      "name": "grass",
      "position": [
        57.535986328125,
        -13.914663696289063,
        -30.0
      ],
      "shortparams": [
        0,
        0,
        0,
        1024
      ],
      "intparams": [
        0,
        1,
        1,
        0,
        0
      ],
      "floatparams": [
        0.0,
        0.0,
        0.0,
        0.0,
        1.471363387541058e-43
      ]
    },
    {
      "name": "grass",
      "position": [
        57.07244873046875,
        -18.24834442138672,
        -30.0
      ],
      "shortparams": [
        0,
        0,
        0,
        1024
      ],
      "intparams": [
        0,
        1,
        1,
        0,
        0
      ],
      "floatparams": [
        0.0,
        0.0,
        0.0,
        0.0,
        1.4293244336113134e-43
      ]
    },
    {
      "name": "chickcoin",
      "position": [
        57.26676635742187,
        -17.68645324707031,
        -31.123089599609376
      ],
      "shortparams": [
        0,
        0,
        0,
        0
      ],
      "intparams": [
        0,
        58,
        0,
        0,
        0
      ],
      "floatparams": [
        0.0,
        0.0,
        0.0,
        0.0,
        0.0
      ]
    },
    {
      "name": "unk15",
      "position": [
        51.467657470703124,
        1.914208221435547,
        -30.0
      ],
      "shortparams": [
        0,
        0,
        0,
        0
      ],
      "intparams": [
        0,
        2,
        0,
        0,
        0
      ],
      "floatparams": [
        0.0,
        0.0,
        0.0,
        0.0,
        0.0
      ]
    },
    {
      "name": "textboxtrigger",
      "position": [
        -33.255853271484376,
        160.1241455078125,
        -18.58000030517578
      ],
      "shortparams": [
        0,
        0,
        0,
        5632
      ],
      "intparams": [
        0,
        41,
        1,
        1,
        0
      ],
      "floatparams": [
        30.0,
        20.0,
        110.0,
        0.0,
        0.0
      ]
    },
    {
      "name": "grass",
      "position": [
        100.79703369140626,
        -54.265106201171875,
        -5.0
      ],
      "shortparams": [
        0,
        0,
        0,
        0
      ],
      "intparams": [
        0,
        0,
        1,
        0,
        0
      ],
      "floatparams": [
        0.0,
        0.0,
        0.0,
        0.0,
        0.0
      ]
    },
    {
      "name": "egg",
      "position": [
        100.79703369140626,
        -54.265106201171875,
        -5.0
      ],
      "shortparams": [
        0,
        0,
        0,
        0
      ],
      "intparams": [
        0,
        2,
        0,
        0,
        0
      ],
      "floatparams": [
        0.0,
        0.0,
        0.0,
        0.0,
        0.0
      ]
    },
    {
      "name": "grass",
      "position": [
        64.90888061523438,
        -35.73854064941406,
        -5.0
      ],
      "shortparams": [
        0,
        0,
        -1,
        -2560
      ],
      "intparams": [
        0,
        17,
        0,
        0,
        0
      ],
      "floatparams": [
        0.0,
        0.0,
        0.0,
        0.0,
        0.0
      ]
    },
    {
      "name": "grass",
      "position": [
        58.916064453125,
        -37.12192993164062,
        -5.0
      ],
      "shortparams": [
        0,
        0,
        -1,
        -2560
      ],
      "intparams": [
        0,
        17,
        0,
        0,
        0
      ],
      "floatparams": [
        0.0,
        0.0,
        0.0,
        0.0,
        0.0
      ]
    },
    {
      "name": "grass",
      "position": [
        61.383636474609375,
        -34.07077331542969,
        -5.0
      ],
      "shortparams": [
        0,
        0,
        -1,
        -2560
      ],
      "intparams": [
        0,
        17,
        0,
        0,
        0
      ],
      "floatparams": [
        0.0,
        0.0,
        0.0,
        0.0,
        0.0
      ]
    },
    {
      "name": "grass",
      "position": [
        52.57509155273438,
        -21.89228057861328,
        -5.0
      ],
      "shortparams": [
        0,
        0,
        -1,
        -6656
      ],
      "intparams": [
        0,
        17,
        0,
        0,
        0
      ],
      "floatparams": [
        0.0,
        0.0,
        0.0,
        0.0,
        0.0
      ]
    },
    {
      "name": "grass",
      "position": [
        56.237115478515626,
        -20.90262451171875,
        -5.0
      ],
      "shortparams": [
        0,
        0,
        -1,
        -6656
      ],
      "intparams": [
        0,
        17,
        0,
        0,
        0
      ],
      "floatparams": [
        0.0,
        0.0,
        0.0,
        0.0,
        0.0
      ]
    },
    {
      "name": "grass",
      "position": [
        59.68995361328125,
        -16.795744323730467,
        -5.0
      ],
      "shortparams": [
        0,
        0,
        -1,
        -6656
      ],
      "intparams": [
        0,
        17,
        0,
        0,
        0
      ],
      "floatparams": [
        0.0,
        0.0,
        0.0,
        0.0,
        0.0
      ]
    },
    {
      "name": "grass",
      "position": [
        -46.02518005371094,
        25.879190063476564,
        -16.0
      ],
      "shortparams": [
        0,
        0,
        0,
        0
      ],
      "intparams": [
        0,
        0,
        1,
        0,
        0
      ],
      "floatparams": [
        0.0,
        0.0,
        0.0,
        0.0,
        0.0
      ]
    },
    {
      "name": "egg",
      "position": [
        -46.02518005371094,
        25.879190063476564,
        -16.0
      ],
      "shortparams": [
        0,
        0,
        0,
        0
      ],
      "intparams": [
        0,
        38,
        0,
        0,
        0
      ],
      "floatparams": [
        0.0,
        0.0,
        0.0,
        0.0,
        0.0
      ]
    },
    {
      "name": "grass",
      "position": [
        56.828826904296875,
        95.59321899414063,
        -10.0
      ],
      "shortparams": [
        0,
        0,
        0,
        0
      ],
      "intparams": [
        0,
        0,
        1,
        0,
        0
      ],
      "floatparams": [
        0.0,
        0.0,
        0.0,
        0.0,
        0.0
      ]
    },
    {
      "name": "egg",
      "position": [
        56.828826904296875,
        95.59321899414063,
        -10.0
      ],
      "shortparams": [
        0,
        0,
        0,
        0
      ],
      "intparams": [
        0,
        20,
        0,
        0,
        0
      ],
      "floatparams": [
        0.0,
        0.0,
        0.0,
        0.0,
        0.0
      ]
    },
    {
      "name": "grass",
      "position": [
        4.6821544647216795,
        149.94459228515626,
        -15.0
      ],
      "shortparams": [
        0,
        0,
        0,
        0
      ],
      "intparams": [
        0,
        0,
        1,
        0,
        0
      ],
      "floatparams": [
        0.0,
        0.0,
        0.0,
        0.0,
        0.0
      ]
    },
    {
      "name": "fruit",
      "position": [
        3.1378265380859376,
        151.87969970703125,
        -15.0
      ],
      "shortparams": [
        0,
        0,
        0,
        0
      ],
      "intparams": [
        0,
        0,
        1,
        1,
        0
      ],
      "floatparams": [
        0.0,
        0.0,
        0.0,
        0.0,
        0.0
      ]
    },
    {
      "name": "fruit",
      "position": [
        6.967109680175781,
        151.166259765625,
        -15.0
      ],
      "shortparams": [
        0,
        0,
        0,
        0
      ],
      "intparams": [
        0,
        1,
        1,
        1,
        0
      ],
      "floatparams": [
        0.0,
        0.0,
        0.0,
        0.0,
        0.0
      ]
    },
    {
      "name": "fruit",
      "position": [
        2.4351806640625,
        148.48720703125,
        -15.0
      ],
      "shortparams": [
        0,
        0,
        0,
        0
      ],
      "intparams": [
        0,
        2,
        1,
        1,
        0
      ],
      "floatparams": [
        0.0,
        0.0,
        0.0,
        0.0,
        0.0
      ]
    },
    {
      "name": "fruit",
      "position": [
        6.302279281616211,
        147.6122314453125,
        -15.0
      ],
      "shortparams": [
        0,
        0,
        0,
        0
      ],
      "intparams": [
        0,
        3,
        1,
        1,
        0
      ],
      "floatparams": [
        0.0,
        0.0,
        0.0,
        0.0,
        0.0
      ]
    },
    {
      "name": "egg",
      "position": [
        4.6821544647216795,
        149.94459228515626,
        -15.0
      ],
      "shortparams": [
        0,
        0,
        0,
        0
      ],
      "intparams": [
        0,
        48,
        0,
        0,
        0
      ],
      "floatparams": [
        0.0,
        0.0,
        0.0,
        0.0,
        0.0
      ]
    },
    {
      "name": "grass",
      "position": [
        48.04615478515625,
        -57.84794921875,
        -1.0
      ],
      "shortparams": [
        0,
        0,
        0,
        0
      ],
      "intparams": [
        0,
        0,
        1,
        0,
        0
      ],
      "floatparams": [
        0.0,
        0.0,
        0.0,
        0.0,
        0.0
      ]
    },
    {
      "name": "egg",
      "position": [
        48.04615478515625,
        -57.84794921875,
        -1.0
      ],
      "shortparams": [
        0,
        0,
        0,
        0
      ],
      "intparams": [
        0,
        49,
        0,
        0,
        0
      ],
      "floatparams": [
        0.0,
        0.0,
        0.0,
        0.0,
        0.0
      ]
    },
    {
      "name": "grass",
      "position": [
        -5.621503448486328,
        -57.38221435546875,
        -1.0
      ],
      "shortparams": [
        0,
        0,
        -1,
        -8960
      ],
      "intparams": [
        0,
        2,
        1,
        0,
        0
      ],
      "floatparams": [
        0.0,
        0.0,
        0.0,
        0.0,
        0.0
      ]
    },
    {
      "name": "grass",
      "position": [
        -5.621503448486328,
        -57.38221435546875,
        -3.5
      ],
      "shortparams": [
        0,
        0,
        -1,
        -8960
      ],
      "intparams": [
        0,
        2,
        1,
        0,
        0
      ],
      "floatparams": [
        0.0,
        0.0,
        0.0,
        0.0,
        0.0
      ]
    },
    {
      "name": "grass",
      "position": [
        -5.621503448486328,
        -57.38221435546875,
        -6.0
      ],
      "shortparams": [
        0,
        0,
        -1,
        -8960
      ],
      "intparams": [
        0,
        1,
        1,
        0,
        0
      ],
      "floatparams": [
        0.0,
        0.0,
        0.0,
        0.0,
        0.0
      ]
    },
    {
      "name": "grass",
      "position": [
        -5.621503448486328,
        -57.38221435546875,
        -11.0
      ],
      "shortparams": [
        0,
        0,
        -1,
        -8960
      ],
      "intparams": [
        0,
        1,
        1,
        0,
        0
      ],
      "floatparams": [
        0.0,
        0.0,
        0.0,
        0.0,
        0.0
      ]
    },
    {
      "name": "grass",
      "position": [
        -5.621503448486328,
        -57.38221435546875,
        -8.5
      ],
      "shortparams": [
        0,
        0,
        -1,
        -8960
      ],
      "intparams": [
        0,
        1,
        1,
        0,
        0
      ],
      "floatparams": [
        0.0,
        0.0,
        0.0,
        0.0,
        0.0
      ]
    },
    {
      "name": "egg",
      "position": [
        77.82750854492187,
        -51.43939208984375,
        -5.0
      ],
      "shortparams": [
        0,
        0,
        0,
        0
      ],
      "intparams": [
        0,
        0,
        0,
        0,
        0
      ],
      "floatparams": [
        0.0,
        0.0,
        0.0,
        0.0,
        0.0
      ]
    },
    {
      "name": "grass",
      "position": [
        77.82750854492187,
        -51.43939208984375,
        -5.0
      ],
      "shortparams": [
        0,
        0,
        0,
        0
      ],
      "intparams": [
        0,
        0,
        1,
        0,
        0
      ],
      "floatparams": [
        0.0,
        0.0,
        0.0,
        0.0,
        0.0
      ]
    },
    {
      "name": "grass",
      "position": [
        42.702459716796874,
        16.751527404785158,
        -30.0
      ],
      "shortparams": [
        0,
        0,
        -1,
        -512
      ],
      "intparams": [
        0,
        0,
        1,
        0,
        0
      ],
      "floatparams": [
        0.0,
        0.0,
        0.0,
        0.0,
        0.0
      ]
    },
    {
      "name": "egg",
      "position": [
        42.702459716796874,
        16.751527404785158,
        -30.0
      ],
      "shortparams": [
        0,
        0,
        -1,
        -512
      ],
      "intparams": [
        0,
        0,
        1,
        0,
        0
      ],
      "floatparams": [
        0.0,
        0.0,
        0.0,
        0.0,
        0.0
      ]
    },
    {
      "name": "checkpoint",
      "position": [
        45.85997619628906,
        8.550874328613281,
        -30.0
      ],
      "shortparams": [
        0,
        0,
        0,
        0
      ],
      "intparams": [
        0,
        2,
        1,
        0,
        0
      ],
      "floatparams": [
        100.0,
        10.0,
        100.0,
        0.0,
        0.0
      ]
    },
    {
      "name": "hoop",
      "position": [
        -14.447773742675782,
        -77.78035888671874,
        -22.401910400390626
      ],
      "shortparams": [
        -1,
        -3840,
        -1,
        -20480
      ],
      "intparams": [
        0,
        3,
        160,
        0,
        0
      ],
      "floatparams": [
        2.0,
        0.0,
        50.0,
        0.0,
        0.0
      ]
    },
    {
      "name": "grass",
      "position": [
        -45.28095703125,
        -68.23604125976563,
        -24.0
      ],
      "shortparams": [
        0,
        0,
        0,
        16384
      ],
      "intparams": [
        0,
        3,
        1,
        0,
        0
      ],
      "floatparams": [
        0.0,
        0.0,
        0.0,
        0.0,
        0.0
      ]
    },
    {
      "name": "grass",
      "position": [
        -18.93348083496094,
        -43.297515869140625,
        -1.0
      ],
      "shortparams": [
        0,
        0,
        0,
        0
      ],
      "intparams": [
        0,
        35,
        0,
        0,
        0
      ],
      "floatparams": [
        0.0,
        0.0,
        0.0,
        0.0,
        0.0
      ]
    },
    {
      "name": "egg",
      "position": [
        -18.93348083496094,
        -43.297515869140625,
        -1.0
      ],
      "shortparams": [
        0,
        0,
        0,
        0
      ],
      "intparams": [
        0,
        47,
        0,
        0,
        0
      ],
      "floatparams": [
        0.0,
        0.0,
        0.0,
        0.0,
        0.0
      ]
    },
    {
      "name": "unk12",
      "position": [
        19.511033630371095,
        137.237841796875,
        -3.9330921173095703
      ],
      "shortparams": [
        0,
        0,
        0,
        256
      ],
      "intparams": [
        0,
        0,
        0,
        0,
        0
      ],
      "floatparams": [
        0.0,
        0.0,
        0.0,
        0.0,
        0.0
      ]
    },
    {
      "name": "textboxtrigger",
      "position": [
        15.308134460449219,
        135.45205078125,
        -10.407727813720703
      ],
      "shortparams": [
        0,
        0,
        0,
        0
      ],
      "intparams": [
        0,
        40,
        1,
        0,
        0
      ],
      "floatparams": [
        50.0,
        60.0,
        120.0,
        0.0,
        0.0
      ]
    },
    {
      "name": "hoop",
      "position": [
        -15.443759155273437,
        4.455731582641602,
        -18.68506317138672
      ],
      "shortparams": [
        0,
        0,
        -1,
        -20480
      ],
      "intparams": [
        0,
        0,
        250,
        0,
        0
      ],
      "floatparams": [
        0.0,
        0.0,
        0.0,
        0.0,
        0.0
      ]
    },
    {
      "name": "hoop",
      "position": [
        -15.807572937011718,
        11.856723022460937,
        -18.68506317138672
      ],
      "shortparams": [
        0,
        0,
        0,
        28672
      ],
      "intparams": [
        0,
        0,
        250,
        0,
        0
      ],
      "floatparams": [
        0.0,
        0.0,
        0.0,
        0.0,
        0.0
      ]
    },
    {
      "name": "hoop",
      "position": [
        1.5241265296936035,
        9.140946960449218,
        -21.7150634765625
      ],
      "shortparams": [
        0,
        0,
        -1,
        -5632
      ],
      "intparams": [
        0,
        0,
        200,
        0,
        0
      ],
      "floatparams": [
        0.0,
        0.0,
        0.0,
        0.0,
        0.0
      ]
    }
  ]
}