{
  "fsize": 81920,
  "entry_size": 80,
  "data": [
    {
      "name": "invisany",
      "position": [
        -538.7880859375,
        905.2532348632812,
        200.0
      ],
      "params": [
        "000000",
        "00ffffe7",
        "0000000000",
        0,
        0,
        "00000000000000000000000000000000",
        4,
        0,
        2,
        0,
        40.0,
        40.0,
        60.0,
        "00000000"
      ]
    },
    {
      "name": "invisany",
      "position": [
        -493.8248596191406,
        257.47332763671875,
        260.0
      ],
      "params": [
        "000000",
        "00000000",
        "0000000000",
        0,
        0,
        "00000000000000000000000000000000",
        10,
        0,
        1,
        0,
        90.0,
        20.0,
        0.0,
        "00000000"
      ]
    },
    {
      "name": "smallcat",
      "position": [
        -1888.6517333984375,
        247.0426788330078,
        258.26605224609375
      ],
      "params": [
        "000000",
        "00000000",
        "0000000000",
        20,
        0,
        "00000000000000000000000000000000",
        0,
        1,
        1,
        0,
        0.0,
        0.0,
        0.0,
        "00000000"
      ]
    },
    {
      "name": "smallcat",
      "position": [
        -1851.64794921875,
        187.43907165527344,
        255.25511169433594
      ],
      "params": [
        "000000",
        "00000000",
        "0000000000",
        20,
        0,
        "00000000000000000000000000000000",
        0,
        1,
        1,
        0,
        0.0,
        0.0,
        0.0,
        "00000000"
      ]
    },
    {
      "name": "smallcat",
      "position": [
        -1924.205810546875,
        183.08885192871094,
        260.4247741699219
      ],
      "params": [
        "000000",
        "00000000",
        "0000000000",
        20,
        0,
        "00000000000000000000000000000000",
        0,
        1,
        1,
        0,
        0.0,
        0.0,
        0.0,
        "00000000"
      ]
    },
    {
      "name": "invisany",
      "position": [
        841.462646484375,
        -917.1072998046875,
        722.381591796875
      ],
      "params": [
        "000000",
        "00000000",
        "0000000000",
        0,
        0,
        "00000000000000000000000000000000",
        9,
        210,
        1,
        0,
        100.0,
        30.0,
        0.0,
        "00000000"
      ]
    },
    {
      "name": "dino",
      "position": [
        841.6407470703125,
        -893.9598999023438,
        720.0
      ],
      "params": [
        "000000",
        "00ffff80",
        "0000000000",
        9,
        0,
        "00000000000000000000000000000000",
        0,
        100,
        0,
        0,
        0.0,
        0.0,
        0.0,
        "00000000"
      ]
    },
    {
      "name": "smallcat",
      "position": [
        -1691.140380859375,
        758.7448120117188,
        170.0
      ],
      "params": [
        "000000",
        "00000000",
        "0000000000",
        1,
        1,
        "00000000000000000000000000000000",
        1,
        1,
        1,
        0,
        0.0,
        0.0,
        0.0,
        "00000000"
      ]
    },
    {
      "name": "smallcat",
      "position": [
        -2009.791015625,
        512.4514770507812,
        264.6915588378906
      ],
      "params": [
        "000000",
        "00000000",
        "0000000000",
        20,
        0,
        "00000000000000000000000000000000",
        0,
        1,
        4,
        0,
        0.0,
        0.0,
        0.0,
        "00000000"
      ]
    },
    {
      "name": "invisany",
      "position": [
        -142.5912322998047,
        -178.40310668945312,
        241.06663513183594
      ],
      "params": [
        "000000",
        "00000000",
        "0000000000",
        0,
        0,
        "00000000000000000000000000000000",
        40,
        0,
        0,
        0,
        170.0,
        0.0,
        0.0,
        "00000000"
      ]
    },
    {
      "name": "smallcat",
      "position": [
        -1724.2633056640625,
        707.8018798828125,
        170.0
      ],
      "params": [
        "000000",
        "00000000",
        "0000000000",
        1,
        1,
        "00000000000000000000000000000000",
        1,
        1,
        1,
        0,
        0.0,
        0.0,
        0.0,
        "00000000"
      ]
    },
    {
      "name": "smallcat",
      "position": [
        -1641.7303466796875,
        709.9180297851562,
        170.0
      ],
      "params": [
        "000000",
        "00000000",
        "0000000000",
        1,
        1,
        "00000000000000000000000000000000",
        1,
        1,
        1,
        0,
        0.0,
        0.0,
        0.0,
        "00000000"
      ]
    },
    {
      "name": "invisany",
      "position": [
        -1605.66162109375,
        471.1584777832031,
        159.99996948242188
      ],
      "params": [
        "000000",
        "00000000",
        "0000000000",
        0,
        0,
        "00000000000000000000000000000000",
        1,
        0,
        1,
        0,
        110.0,
        20.0,
        0.0,
        "00000000"
      ]
    },
    {
      "name": "smallcat",
      "position": [
        -1666.0667724609375,
        671.168212890625,
        170.0
      ],
      "params": [
        "000000",
        "00000000",
        "0000000000",
        1,
        1,
        "00000000000000000000000000000000",
        1,
        1,
        1,
        0,
        0.0,
        0.0,
        0.0,
        "00000000"
      ]
    },
    {
      "name": "smallcat",
      "position": [
        545.5199584960938,
        320.8785705566406,
        160.0
      ],
      "params": [
        "000000",
        "00ffff90",
        "0000000000",
        7,
        0,
        "00000000000000000000000000000000",
        0,
        0,
        1,
        0,
        0.0,
        0.0,
        0.0,
        "00000000"
      ]
    },
    {
      "name": "smallcat",
      "position": [
        537.398681640625,
        267.94256591796875,
        160.0
      ],
      "params": [
        "000000",
        "00ffff90",
        "0000000000",
        7,
        0,
        "00000000000000000000000000000000",
        0,
        0,
        1,
        0,
        0.0,
        0.0,
        0.0,
        "00000000"
      ]
    },
    {
      "name": "smallcat",
      "position": [
        590.5267944335938,
        286.2392272949219,
        160.0
      ],
      "params": [
        "000000",
        "00ffff90",
        "0000000000",
        7,
        0,
        "00000000000000000000000000000000",
        0,
        0,
        1,
        0,
        0.0,
        0.0,
        0.0,
        "00000000"
      ]
    },
    {
      "name": "smallcat",
      "position": [
        638.5658569335938,
        248.74935913085938,
        160.0
      ],
      "params": [
        "000000",
        "00ffff90",
        "0000000000",
        7,
        0,
        "00000000000000000000000000000000",
        0,
        0,
        1,
        0,
        0.0,
        0.0,
        0.0,
        "00000000"
      ]
    },
    {
      "name": "smallcat",
      "position": [
        527.8701171875,
        204.2875518798828,
        160.0
      ],
      "params": [
        "000000",
        "00ffff90",
        "0000000000",
        7,
        0,
        "00000000000000000000000000000000",
        0,
        0,
        1,
        0,
        0.0,
        0.0,
        0.0,
        "00000000"
      ]
    },
    {
      "name": "invisany",
      "position": [
        369.78411865234375,
        599.3489379882812,
        159.99996948242188
      ],
      "params": [
        "000000",
        "00fffff0",
        "0000000000",
        0,
        0,
        "00000000000000000000000000000000",
        7,
        0,
        1,
        0,
        70.0,
        30.0,
        60.0,
        "00000000"
      ]
    },
    {
      "name": "invisany",
      "position": [
        -1336.1558837890625,
        334.04925537109375,
        160.0999755859375
      ],
      "params": [
        "000000",
        "00fffff7",
        "0000000000",
        0,
        0,
        "00000000000000000000000000000000",
        3,
        0,
        1,
        0,
        150.0,
        30.0,
        0.0,
        "00000000"
      ]
    },
    {
      "name": "dino",
      "position": [
        -1421.524169921875,
        310.0794677734375,
        159.99996948242188
      ],
      "params": [
        "000000",
        "00000040",
        "0000000000",
        3,
        0,
        "00000000000000000000000000000000",
        30,
        0,
        0,
        0,
        0.0,
        0.0,
        0.0,
        "00000000"
      ]
    },
    {
      "name": "dino",
      "position": [
        -1418.41650390625,
        402.3149108886719,
        159.99996948242188
      ],
      "params": [
        "000000",
        "00000040",
        "0000000000",
        3,
        0,
        "00000000000000000000000000000000",
        30,
        0,
        0,
        0,
        0.0,
        0.0,
        0.0,
        "00000000"
      ]
    },
    {
      "name": "smallcat",
      "position": [
        582.0643310546875,
        226.47235107421875,
        160.0
      ],
      "params": [
        "000000",
        "00ffff90",
        "0000000000",
        7,
        0,
        "00000000000000000000000000000000",
        0,
        0,
        1,
        0,
        0.0,
        0.0,
        0.0,
        "00000000"
      ]
    },
    {
      "name": "dino",
      "position": [
        618.1905517578125,
        147.88137817382812,
        160.0
      ],
      "params": [
        "000000",
        "00ffff90",
        "0000000000",
        7,
        0,
        "00000000000000000000000000000000",
        30,
        0,
        1,
        0,
        0.0,
        0.0,
        0.0,
        "00000000"
      ]
    },
    {
      "name": "invisany",
      "position": [
        264.8883361816406,
        -76.5049057006836,
        170.49143981933594
      ],
      "params": [
        "000000",
        "00000000",
        "0000000000",
        0,
        0,
        "00000000000000000000000000000000",
        2,
        0,
        2,
        0,
        10.0,
        40.0,
        130.0,
        "00000000"
      ]
    },
    {
      "name": "smallcat",
      "position": [
        413.18133544921875,
        88.6724853515625,
        165.113525390625
      ],
      "params": [
        "000000",
        "00000000",
        "0000000000",
        2,
        0,
        "00000000000000000000000000000000",
        1,
        1,
        2,
        0,
        0.0,
        0.0,
        0.0,
        "00000000"
      ]
    },
    {
      "name": "smallcat",
      "position": [
        368.80279541015625,
        167.9790802001953,
        165.113525390625
      ],
      "params": [
        "000000",
        "00000000",
        "0000000000",
        2,
        0,
        "00000000000000000000000000000000",
        1,
        1,
        2,
        0,
        0.0,
        0.0,
        0.0,
        "00000000"
      ]
    },
    {
      "name": "smallcat",
      "position": [
        415.54180908203125,
        143.27621459960938,
        174.2947235107422
      ],
      "params": [
        "000000",
        "00000000",
        "0000000000",
        2,
        0,
        "00000000000000000000000000000000",
        1,
        1,
        2,
        0,
        0.0,
        0.0,
        0.0,
        "00000000"
      ]
    },
    {
      "name": "smallcat",
      "position": [
        430.7340393066406,
        212.37615966796875,
        165.113525390625
      ],
      "params": [
        "000000",
        "00000000",
        "0000000000",
        2,
        0,
        "00000000000000000000000000000000",
        1,
        1,
        2,
        0,
        0.0,
        0.0,
        0.0,
        "00000000"
      ]
    },
    {
      "name": "smallcat",
      "position": [
        470.4075622558594,
        124.78569793701172,
        165.113525390625
      ],
      "params": [
        "000000",
        "00000000",
        "0000000000",
        2,
        0,
        "00000000000000000000000000000000",
        1,
        1,
        2,
        0,
        0.0,
        0.0,
        0.0,
        "00000000"
      ]
    },
    {
      "name": "armadillo",
      "position": [
        -216.88719177246094,
        174.29244995117188,
        229.99996948242188
      ],
      "params": [
        "000000",
        "00fffff0",
        "0000000000",
        40,
        0,
        "00000000000000000000000000000000",
        20,
        0,
        0,
        0,
        0.0,
        0.0,
        0.0,
        "00000000"
      ]
    },
    {
      "name": "armadillo",
      "position": [
        -418.356689453125,
        94.12416076660156,
        229.99996948242188
      ],
      "params": [
        "000000",
        "00fffff0",
        "0000000000",
        40,
        0,
        "00000000000000000000000000000000",
        20,
        0,
        0,
        0,
        0.0,
        0.0,
        0.0,
        "00000000"
      ]
    },
    {
      "name": "dino",
      "position": [
        -411.3118896484375,
        35.395362854003906,
        229.99996948242188
      ],
      "params": [
        "000000",
        "00000010",
        "0000000000",
        40,
        1,
        "00000000000000000000000000000000",
        30,
        0,
        0,
        0,
        0.0,
        0.0,
        0.0,
        "00000000"
      ]
    },
    {
      "name": "dino",
      "position": [
        -174.05996704101562,
        -29.51912498474121,
        229.99996948242188
      ],
      "params": [
        "000000",
        "00000010",
        "0000000000",
        40,
        1,
        "00000000000000000000000000000000",
        30,
        0,
        0,
        0,
        0.0,
        0.0,
        0.0,
        "00000000"
      ]
    },
    {
      "name": "bat",
      "position": [
        -144.6582489013672,
        860.5970458984375,
        159.99996948242188
      ],
      "params": [
        "000000",
        "00000000",
        "0000000000",
        6,
        1,
        "00000000000000000000000000000000",
        30,
        50,
        0,
        0,
        0.0,
        0.0,
        0.0,
        "00000000"
      ]
    },
    {
      "name": "smallcat",
      "position": [
        -4.472132205963135,
        567.9994506835938,
        160.0
      ],
      "params": [
        "000000",
        "00000000",
        "0000000000",
        6,
        0,
        "00000000000000000000000000000000",
        0,
        1,
        1,
        0,
        0.0,
        0.0,
        0.0,
        "00000000"
      ]
    },
    {
      "name": "smallcat",
      "position": [
        -53.07540512084961,
        525.4993286132812,
        160.0
      ],
      "params": [
        "000000",
        "00000000",
        "0000000000",
        6,
        0,
        "00000000000000000000000000000000",
        0,
        1,
        1,
        0,
        0.0,
        0.0,
        0.0,
        "00000000"
      ]
    },
    {
      "name": "smallcat",
      "position": [
        -4.8442254066467285,
        516.5823364257812,
        160.0
      ],
      "params": [
        "000000",
        "00000000",
        "0000000000",
        6,
        0,
        "00000000000000000000000000000000",
        0,
        1,
        1,
        0,
        0.0,
        0.0,
        0.0,
        "00000000"
      ]
    },
    {
      "name": "bat",
      "position": [
        18.08633804321289,
        479.50836181640625,
        159.99996948242188
      ],
      "params": [
        "000000",
        "00000000",
        "0000000000",
        6,
        1,
        "00000000000000000000000000000000",
        30,
        50,
        0,
        0,
        0.0,
        0.0,
        0.0,
        "00000000"
      ]
    },
    {
      "name": "dino",
      "position": [
        61.6985969543457,
        612.468017578125,
        160.0
      ],
      "params": [
        "000000",
        "00000000",
        "0000000000",
        6,
        0,
        "00000000000000000000000000000000",
        30,
        0,
        0,
        0,
        0.0,
        0.0,
        0.0,
        "00000000"
      ]
    },
    {
      "name": "dino",
      "position": [
        -148.140625,
        826.5111083984375,
        160.0
      ],
      "params": [
        "000000",
        "00000000",
        "0000000000",
        6,
        0,
        "00000000000000000000000000000000",
        30,
        0,
        0,
        0,
        0.0,
        0.0,
        0.0,
        "00000000"
      ]
    },
    {
      "name": "smallcat",
      "position": [
        -42.938934326171875,
        568.894287109375,
        160.0
      ],
      "params": [
        "000000",
        "00000000",
        "0000000000",
        6,
        0,
        "00000000000000000000000000000000",
        0,
        1,
        1,
        0,
        0.0,
        0.0,
        0.0,
        "00000000"
      ]
    },
    {
      "name": "smallcat",
      "position": [
        -180.75894165039062,
        751.2105102539062,
        160.0
      ],
      "params": [
        "000000",
        "00000000",
        "0000000000",
        6,
        0,
        "00000000000000000000000000000000",
        0,
        1,
        1,
        0,
        0.0,
        0.0,
        0.0,
        "00000000"
      ]
    },
    {
      "name": "smallcat",
      "position": [
        -218.5491943359375,
        734.2718505859375,
        160.0
      ],
      "params": [
        "000000",
        "00000000",
        "0000000000",
        6,
        0,
        "00000000000000000000000000000000",
        0,
        1,
        1,
        0,
        0.0,
        0.0,
        0.0,
        "00000000"
      ]
    },
    {
      "name": "smallcat",
      "position": [
        -196.41607666015625,
        673.0352172851562,
        160.0
      ],
      "params": [
        "000000",
        "00000000",
        "0000000000",
        6,
        0,
        "00000000000000000000000000000000",
        0,
        1,
        1,
        0,
        0.0,
        0.0,
        0.0,
        "00000000"
      ]
    },
    {
      "name": "smallcat",
      "position": [
        -156.02781677246094,
        701.703125,
        160.0
      ],
      "params": [
        "000000",
        "00000000",
        "0000000000",
        6,
        0,
        "00000000000000000000000000000000",
        0,
        1,
        1,
        0,
        0.0,
        0.0,
        0.0,
        "00000000"
      ]
    },
    {
      "name": "invisany",
      "position": [
        -1373.3109130859375,
        974.301513671875,
        290.8308410644531
      ],
      "params": [
        "000000",
        "00000000",
        "0000000000",
        0,
        0,
        "00000000000000000000000000000000",
        4,
        0,
        0,
        0,
        120.0,
        0.0,
        0.0,
        "00000000"
      ]
    },
    {
      "name": "smallcat",
      "position": [
        -2030.3016357421875,
        455.4181213378906,
        256.6649169921875
      ],
      "params": [
        "000000",
        "00000000",
        "0000000000",
        20,
        0,
        "00000000000000000000000000000000",
        0,
        1,
        4,
        0,
        0.0,
        0.0,
        0.0,
        "00000000"
      ]
    },
    {
      "name": "smallcat",
      "position": [
        -2061.25927734375,
        527.4551391601562,
        256.6649169921875
      ],
      "params": [
        "000000",
        "00000000",
        "0000000000",
        20,
        0,
        "00000000000000000000000000000000",
        0,
        1,
        4,
        0,
        0.0,
        0.0,
        0.0,
        "00000000"
      ]
    },
    {
      "name": "smallcat",
      "position": [
        -2073.607666015625,
        479.78363037109375,
        256.6649169921875
      ],
      "params": [
        "000000",
        "00000000",
        "0000000000",
        20,
        0,
        "00000000000000000000000000000000",
        0,
        1,
        4,
        0,
        0.0,
        0.0,
        0.0,
        "00000000"
      ]
    },
    {
      "name": "smallcat",
      "position": [
        -2053.8251953125,
        411.6950988769531,
        255.7537841796875
      ],
      "params": [
        "000000",
        "00000000",
        "0000000000",
        20,
        0,
        "00000000000000000000000000000000",
        0,
        1,
        4,
        0,
        0.0,
        0.0,
        0.0,
        "00000000"
      ]
    },
    {
      "name": "smallcat",
      "position": [
        -1993.6993408203125,
        425.8022155761719,
        263.082275390625
      ],
      "params": [
        "000000",
        "00000000",
        "0000000000",
        20,
        0,
        "00000000000000000000000000000000",
        0,
        1,
        4,
        0,
        0.0,
        0.0,
        0.0,
        "00000000"
      ]
    },
    {
      "name": "smallcat",
      "position": [
        -2003.665771484375,
        474.4559326171875,
        264.295654296875
      ],
      "params": [
        "000000",
        "00000000",
        "0000000000",
        20,
        0,
        "00000000000000000000000000000000",
        0,
        1,
        4,
        0,
        0.0,
        0.0,
        0.0,
        "00000000"
      ]
    },
    {
      "name": "smallcat",
      "position": [
        -1935.0914306640625,
        244.3994903564453,
        255.0127410888672
      ],
      "params": [
        "000000",
        "00000000",
        "0000000000",
        20,
        0,
        "00000000000000000000000000000000",
        0,
        1,
        1,
        0,
        0.0,
        0.0,
        0.0,
        "00000000"
      ]
    },
    {
      "name": "smallcat",
      "position": [
        -1864.1864013671875,
        143.90106201171875,
        260.86334228515625
      ],
      "params": [
        "000000",
        "00000000",
        "0000000000",
        20,
        0,
        "00000000000000000000000000000000",
        0,
        1,
        1,
        0,
        0.0,
        0.0,
        0.0,
        "00000000"
      ]
    },
    {
      "name": "smallcat",
      "position": [
        -1797.7236328125,
        180.31503295898438,
        256.55279541015625
      ],
      "params": [
        "000000",
        "00000000",
        "0000000000",
        20,
        0,
        "00000000000000000000000000000000",
        0,
        1,
        1,
        0,
        0.0,
        0.0,
        0.0,
        "00000000"
      ]
    },
    {
      "name": "smallcat",
      "position": [
        -2012.6556396484375,
        760.9744262695312,
        255.86622619628906
      ],
      "params": [
        "000000",
        "00000000",
        "0000000000",
        4,
        0,
        "00000000000000000000000000000000",
        0,
        1,
        1,
        0,
        0.0,
        0.0,
        0.0,
        "00000000"
      ]
    },
    {
      "name": "smallcat",
      "position": [
        -1968.060302734375,
        770.2743530273438,
        262.7239685058594
      ],
      "params": [
        "000000",
        "00000000",
        "0000000000",
        4,
        0,
        "00000000000000000000000000000000",
        0,
        1,
        1,
        0,
        0.0,
        0.0,
        0.0,
        "00000000"
      ]
    },
    {
      "name": "smallcat",
      "position": [
        -1946.314697265625,
        820.8363647460938,
        259.0995178222656
      ],
      "params": [
        "000000",
        "00000000",
        "0000000000",
        4,
        0,
        "00000000000000000000000000000000",
        0,
        1,
        1,
        0,
        0.0,
        0.0,
        0.0,
        "00000000"
      ]
    },
    {
      "name": "smallcat",
      "position": [
        -1912.0491943359375,
        855.1076049804688,
        259.3550109863281
      ],
      "params": [
        "000000",
        "00000000",
        "0000000000",
        4,
        0,
        "00000000000000000000000000000000",
        0,
        1,
        1,
        0,
        0.0,
        0.0,
        0.0,
        "00000000"
      ]
    },
    {
      "name": "smallcat",
      "position": [
        -1960.87841796875,
        874.51025390625,
        255.81033325195312
      ],
      "params": [
        "000000",
        "00000000",
        "0000000000",
        4,
        0,
        "00000000000000000000000000000000",
        0,
        1,
        1,
        0,
        0.0,
        0.0,
        0.0,
        "00000000"
      ]
    },
    {
      "name": "smallcat",
      "position": [
        -1987.576416015625,
        913.3576049804688,
        267.1124267578125
      ],
      "params": [
        "000000",
        "00000000",
        "0000000000",
        4,
        0,
        "00000000000000000000000000000000",
        0,
        1,
        1,
        0,
        0.0,
        0.0,
        0.0,
        "00000000"
      ]
    },
    {
      "name": "smallcat",
      "position": [
        -2014.3519287109375,
        851.0946044921875,
        260.3010559082031
      ],
      "params": [
        "000000",
        "00000000",
        "0000000000",
        4,
        0,
        "00000000000000000000000000000000",
        0,
        1,
        1,
        0,
        0.0,
        0.0,
        0.0,
        "00000000"
      ]
    },
    {
      "name": "smallcat",
      "position": [
        -1994.727783203125,
        803.5524291992188,
        255.44119262695312
      ],
      "params": [
        "000000",
        "00000000",
        "0000000000",
        4,
        0,
        "00000000000000000000000000000000",
        0,
        1,
        1,
        0,
        0.0,
        0.0,
        0.0,
        "00000000"
      ]
    },
    {
      "name": "smallcat",
      "position": [
        -2042.0103759765625,
        798.6312255859375,
        257.91705322265625
      ],
      "params": [
        "000000",
        "00000000",
        "0000000000",
        4,
        0,
        "00000000000000000000000000000000",
        0,
        1,
        1,
        0,
        0.0,
        0.0,
        0.0,
        "00000000"
      ]
    },
    {
      "name": "invisany",
      "position": [
        -1521.910888671875,
        76.99432373046875,
        253.8000030517578
      ],
      "params": [
        "000000",
        "00fffff0",
        "0000000000",
        0,
        0,
        "00000000000000000000000000000000",
        16,
        20,
        1,
        0,
        160.0,
        10.0,
        0.0,
        "00000000"
      ]
    },
    {
      "name": "dino",
      "position": [
        -1469.109375,
        79.57719421386719,
        250.0
      ],
      "params": [
        "000000",
        "00ffffc0",
        "0000000000",
        16,
        1,
        "00000000000000000000000000000000",
        50,
        0,
        0,
        0,
        0.0,
        0.0,
        0.0,
        "00000000"
      ]
    },
    {
      "name": "invisany",
      "position": [
        -80.82211303710938,
        462.8217468261719,
        160.0
      ],
      "params": [
        "000000",
        "00000000",
        "0000000000",
        0,
        0,
        "00000000000000000000000000000000",
        6,
        0,
        1,
        0,
        200.0,
        20.0,
        0.0,
        "00000000"
      ]
    }
  ]
}